commondata_languages/__init__.py
commondata_languages/__main__.py
commondata_languages/data.py
commondata_languages-1.1.0.dist-info/LICENSE
commondata_languages-1.1.0.dist-info/METADATA
commondata_languages-1.1.0.dist-info/WHEEL
commondata_languages-1.1.0.dist-info/RECORD
