Metadata-Version: 2.3
Name: commondata-languages
Version: 1.1.0
Summary: Work with ISO 639-1, ISO 639-2B, ISO 639-2T, and ISO 639-3 language data.
Author: Shiv Deepak
Author-email: shivdeepak@gmail.com
Requires-Python: >=3.13
Classifier: Programming Language :: Python :: 3
Classifier: Programming Language :: Python :: 3.13
Requires-Dist: rapidfuzz (>=3.12.1,<4.0.0)
